w2w_ecs_autopublish_dummy/__init__.py
w2w_ecs_autopublish_dummy/main.py
w2w_ecs_autopublish_dummy-0.0.8.dist-info/LICENSE
w2w_ecs_autopublish_dummy-0.0.8.dist-info/METADATA
w2w_ecs_autopublish_dummy-0.0.8.dist-info/WHEEL
w2w_ecs_autopublish_dummy-0.0.8.dist-info/entry_points.txt
w2w_ecs_autopublish_dummy-0.0.8.dist-info/top_level.txt
w2w_ecs_autopublish_dummy-0.0.8.dist-info/RECORD
