Metadata-Version: 2.1
Name: w2w-ecs-autopublish-dummy
Version: 0.0.8
Summary: A test to try PYPI package publishing using CI.
Author-email: Oriol Tintó <oriol.tinto@lmu.de>
Project-URL: Homepage, https://gitlab.physik.uni-muenchen.de/Oriol.Tinto/w2w_ecs_autopublish_dummy
Classifier: Programming Language :: Python :: 3
Classifier: License :: OSI Approved :: MIT License
Classifier: Operating System :: OS Independent
Requires-Python: >=3.8
License-File: LICENSE
